CHANGELOG.txt
README.txt
setup.py
presentation/index.html
presentation/images/pull_trunk.png
presentation/images/rebase.png
presentation/ui/default/blank.gif
presentation/ui/default/bodybg.gif
presentation/ui/default/framing.css
presentation/ui/default/iepngfix.htc
presentation/ui/default/opera.css
presentation/ui/default/outline.css
presentation/ui/default/pretty.css
presentation/ui/default/print.css
presentation/ui/default/s5-core.css
presentation/ui/default/slides.css
presentation/ui/default/slides.js
presentation/ui/i18n/00_head.txt
presentation/ui/i18n/bg-shade.png
presentation/ui/i18n/bg-slide.jpg
presentation/ui/i18n/framing.css
presentation/ui/i18n/pretty.css
presentation/ui/i18n/s5-core.css
presentation/ui/i18n/slides.css
setup_helper/__init__.py
setup_helper/publish_docs.py
src/sv/__init__.py
src/sv/command.py
src/sv/sv.py
src/sv.egg-info/PKG-INFO
src/sv.egg-info/SOURCES.txt
src/sv.egg-info/dependency_links.txt
src/sv.egg-info/entry_points.txt
src/sv.egg-info/not-zip-safe
src/sv.egg-info/requires.txt
src/sv.egg-info/top_level.txt
tests/__init__.py
tests/fixtures.py
tests/test_command.py
tests/test_sv.py