Metadata-Version: 1.0
Name: sv
Version: 0.2.2
Summary: subversion wrapper to simplify the task of branching and merging
Home-page: http://code.google.com/p/sv-subversion/
Author: Luke Opperman, Dan Bravender, Kumar McMillan
Author-email: loppear@gmail.com
License: GPL
Keywords: sv subversion branching merging
Platform: UNKNOWN
